[
    {
        "Name":  "1.3.5-backpacks_mod-1.21-1.21.1.jar",
        "Path":  "C:\\Users\\nacho\\AppData\\Roaming\\.minecraft\\mods\\1.3.5-backpacks_mod-1.21-1.21.1.jar",
        "Hash":  "31238a7bcea93a5b51f7ff85b7681f71d70d5b6a"
    },
    {
        "Name":  "accessories-neoforge-1.1.0-beta.52+1.21.1.jar",
        "Path":  "C:\\Users\\nacho\\AppData\\Roaming\\.minecraft\\mods\\accessories-neoforge-1.1.0-beta.52+1.21.1.jar",
        "Hash":  "c2b288a7fa9ae595e3fa9cc7deee56306474e300"
    },
    {
        "Name":  "AI-Improvements-1.21-0.5.3.jar",
        "Path":  "C:\\Users\\nacho\\AppData\\Roaming\\.minecraft\\mods\\AI-Improvements-1.21-0.5.3.jar",
        "Hash":  "b4a8e11384454bcc341043b251db7fb5afdfdf45"
    },
    {
        "Name":  "amendments-1.21-2.0.13-neoforge.jar",
        "Path":  "C:\\Users\\nacho\\AppData\\Roaming\\.minecraft\\mods\\amendments-1.21-2.0.13-neoforge.jar",
        "Hash":  "8ff88f9b6d422c7d2a1f20c318fa6f4edf0eab8a"
    },
    {
        "Name":  "another_furniture-neoforge-4.0.1.jar",
        "Path":  "C:\\Users\\nacho\\AppData\\Roaming\\.minecraft\\mods\\another_furniture-neoforge-4.0.1.jar",
        "Hash":  "cad17199d94695b20a630b48cdc409532a0fed55"
    },
    {
        "Name":  "appleskin-neoforge-mc1.21-3.0.7.jar",
        "Path":  "C:\\Users\\nacho\\AppData\\Roaming\\.minecraft\\mods\\appleskin-neoforge-mc1.21-3.0.7.jar",
        "Hash":  "8f76d97a7f61f8d61db6d84a83baf29a3bb56330"
    },
    {
        "Name":  "architectury-13.0.8-neoforge.jar",
        "Path":  "C:\\Users\\nacho\\AppData\\Roaming\\.minecraft\\mods\\architectury-13.0.8-neoforge.jar",
        "Hash":  "6ca11d3cc136bf69bb8f4d56982481eb85b5100b"
    },
    {
        "Name":  "artifacts-neoforge-13.1.0.jar",
        "Path":  "C:\\Users\\nacho\\AppData\\Roaming\\.minecraft\\mods\\artifacts-neoforge-13.1.0.jar",
        "Hash":  "2f3fb112b836415d3128b1888779b8b93323a871"
    },
    {
        "Name":  "AsyncParticles-3.4.0-beta.1+1.21.1.jar",
        "Path":  "C:\\Users\\nacho\\AppData\\Roaming\\.minecraft\\mods\\AsyncParticles-3.4.0-beta.1+1.21.1.jar",
        "Hash":  "3591df55ff3396ec9fd24cd5a500e7438fa3b939"
    },
    {
        "Name":  "azurelib-neo-1.21.1-2.3.28.jar",
        "Path":  "C:\\Users\\nacho\\AppData\\Roaming\\.minecraft\\mods\\azurelib-neo-1.21.1-2.3.28.jar",
        "Hash":  "73781a1257bf7d3e6046a1669b90af29e75c07e1"
    },
    {
        "Name":  "badpackets-neo-0.8.2.jar",
        "Path":  "C:\\Users\\nacho\\AppData\\Roaming\\.minecraft\\mods\\badpackets-neo-0.8.2.jar",
        "Hash":  "6a29963a30afd7fa8993b97e4f870460b3f51323"
    },
    {
        "Name":  "balm-neoforge-1.21.1-21.0.55.jar",
        "Path":  "C:\\Users\\nacho\\AppData\\Roaming\\.minecraft\\mods\\balm-neoforge-1.21.1-21.0.55.jar",
        "Hash":  "288003dfab9ef7d4aa600c9325cb64ce861c3d4d"
    },
    {
        "Name":  "BetterBeacons-NeoForge-1.21.1-2.1.1.jar",
        "Path":  "C:\\Users\\nacho\\AppData\\Roaming\\.minecraft\\mods\\BetterBeacons-NeoForge-1.21.1-2.1.1.jar",
        "Hash":  "036db02525151be4fa0abd3e4f6f58104efd16ee"
    },
    {
        "Name":  "BetterTridents-v21.1.0-1.21.1-NeoForge.jar",
        "Path":  "C:\\Users\\nacho\\AppData\\Roaming\\.minecraft\\mods\\BetterTridents-v21.1.0-1.21.1-NeoForge.jar",
        "Hash":  "0f0903bf03f2dda02bf4c12f96c2bd52acb492c7"
    },
    {
        "Name":  "better_modlist-1.1.21.jar",
        "Path":  "C:\\Users\\nacho\\AppData\\Roaming\\.minecraft\\mods\\better_modlist-1.1.21.jar",
        "Hash":  "9da2a1c4f5450695dd3cef2b760ef6ddb3f3e031"
    },
    {
        "Name":  "better_tooltips-1.0.3.jar",
        "Path":  "C:\\Users\\nacho\\AppData\\Roaming\\.minecraft\\mods\\better_tooltips-1.0.3.jar",
        "Hash":  "ac67bc12905121dc52d6403edd2c4cc8d39a6b67"
    },
    {
        "Name":  "blueprint-1.21.1-8.0.8.jar",
        "Path":  "C:\\Users\\nacho\\AppData\\Roaming\\.minecraft\\mods\\blueprint-1.21.1-8.0.8.jar",
        "Hash":  "9f9549cecaee3f4cb03d9c829b148a110a0efb54"
    },
    {
        "Name":  "bookshelf-neoforge-1.21.1-21.1.80.jar",
        "Path":  "C:\\Users\\nacho\\AppData\\Roaming\\.minecraft\\mods\\bookshelf-neoforge-1.21.1-21.1.80.jar",
        "Hash":  "04faab5a3e3fde909601145ac7dd8d806087958d"
    },
    {
        "Name":  "cadeditor-1.21.1-0.1.0-neoforge.jar",
        "Path":  "C:\\Users\\nacho\\AppData\\Roaming\\.minecraft\\mods\\cadeditor-1.21.1-0.1.0-neoforge.jar",
        "Hash":  "29bd5eb4dbc2d395117ef6d29cd45b93c005e821"
    },
    {
        "Name":  "caelus-neoforge-7.0.1+1.21.1.jar",
        "Path":  "C:\\Users\\nacho\\AppData\\Roaming\\.minecraft\\mods\\caelus-neoforge-7.0.1+1.21.1.jar",
        "Hash":  "e4c2e1af4e3082d68f7df75f7c8ce30116d71515"
    },
    {
        "Name":  "CerbonsAPI-NeoForge-1.21-1.3.0.jar",
        "Path":  "C:\\Users\\nacho\\AppData\\Roaming\\.minecraft\\mods\\CerbonsAPI-NeoForge-1.21-1.3.0.jar",
        "Hash":  "3f0d3eed4633d9ef3a713de4b39ee4e683aa9389"
    },
    {
        "Name":  "chatanimation-neoforge-1.21.1-1.1.3.jar",
        "Path":  "C:\\Users\\nacho\\AppData\\Roaming\\.minecraft\\mods\\chatanimation-neoforge-1.21.1-1.1.3.jar",
        "Hash":  "a56aae316e52564a7e49b0aadc6c49441ef9f62d"
    },
    {
        "Name":  "chat_heads-0.14.2-neoforge-1.21.jar",
        "Path":  "C:\\Users\\nacho\\AppData\\Roaming\\.minecraft\\mods\\chat_heads-0.14.2-neoforge-1.21.jar",
        "Hash":  "ec242eb18f8479c2f4cedb6c79a63686dc91c55e"
    },
    {
        "Name":  "Chimes-v2.0.3-1.21.1-NeoForge.jar",
        "Path":  "C:\\Users\\nacho\\AppData\\Roaming\\.minecraft\\mods\\Chimes-v2.0.3-1.21.1-NeoForge.jar",
        "Hash":  "9d4bfc5de7f609cbd376df157d9cd7afc3d77591"
    },
    {
        "Name":  "Chunky-NeoForge-1.4.23.jar",
        "Path":  "C:\\Users\\nacho\\AppData\\Roaming\\.minecraft\\mods\\Chunky-NeoForge-1.4.23.jar",
        "Hash":  "ab0c74743a653020fe2dfc4986b43e893947f3e9"
    },
    {
        "Name":  "chunky-offline-v1.1.0.jar",
        "Path":  "C:\\Users\\nacho\\AppData\\Roaming\\.minecraft\\mods\\chunky-offline-v1.1.0.jar",
        "Hash":  "5783f3ec055a3e5f369cfd169d62c2c2f4da44d4"
    },
    {
        "Name":  "cloth-config-15.0.140-neoforge.jar",
        "Path":  "C:\\Users\\nacho\\AppData\\Roaming\\.minecraft\\mods\\cloth-config-15.0.140-neoforge.jar",
        "Hash":  "c3e5733ba4503b102589a026000fd5ce0212f6f2"
    },
    {
        "Name":  "cobweb-neoforge-1.21-1.4.0.jar",
        "Path":  "C:\\Users\\nacho\\AppData\\Roaming\\.minecraft\\mods\\cobweb-neoforge-1.21-1.4.0.jar",
        "Hash":  "5ae5dbf4184a62b9ff5bd31f6f8ba62943dd197d"
    },
    {
        "Name":  "CombatNouveau-v21.1.1-1.21.1-NeoForge.jar",
        "Path":  "C:\\Users\\nacho\\AppData\\Roaming\\.minecraft\\mods\\CombatNouveau-v21.1.1-1.21.1-NeoForge.jar",
        "Hash":  "11cff4ff6ca24cf0889d73c2465a922564afe0dd"
    },
    {
        "Name":  "coroutil-neoforge-1.21.0-1.3.8.jar",
        "Path":  "C:\\Users\\nacho\\AppData\\Roaming\\.minecraft\\mods\\coroutil-neoforge-1.21.0-1.3.8.jar",
        "Hash":  "b044c51d00d60b5645a0c0890812935cd933555f"
    },
    {
        "Name":  "cratedelight-25.09.22-1.21-neoforge.jar",
        "Path":  "C:\\Users\\nacho\\AppData\\Roaming\\.minecraft\\mods\\cratedelight-25.09.22-1.21-neoforge.jar",
        "Hash":  "3cfe8feb1962e0b69d7a47e44458533489d62e4d"
    },
    {
        "Name":  "crittersandcompanions-neoforge-1.21.1-2.3.4.jar",
        "Path":  "C:\\Users\\nacho\\AppData\\Roaming\\.minecraft\\mods\\crittersandcompanions-neoforge-1.21.1-2.3.4.jar",
        "Hash":  "c32ae5df533d081f845a153ab67c8d1c61cf339f"
    },
    {
        "Name":  "cryonicconfig-neoforge-1.0.0+mc1.21.11.jar",
        "Path":  "C:\\Users\\nacho\\AppData\\Roaming\\.minecraft\\mods\\cryonicconfig-neoforge-1.0.0+mc1.21.11.jar",
        "Hash":  "45b7240ad5cd561511ae3f80eea4cbfc110dae70"
    },
    {
        "Name":  "curios-neoforge-9.5.1+1.21.1.jar",
        "Path":  "C:\\Users\\nacho\\AppData\\Roaming\\.minecraft\\mods\\curios-neoforge-9.5.1+1.21.1.jar",
        "Hash":  "418fcd42e3a7844c9bdc71c9b6401fdb3894e0c4"
    },
    {
        "Name":  "CutThrough-v21.1.0-1.21.1-NeoForge.jar",
        "Path":  "C:\\Users\\nacho\\AppData\\Roaming\\.minecraft\\mods\\CutThrough-v21.1.0-1.21.1-NeoForge.jar",
        "Hash":  "550f272c140566f0961c1bb3fdfb1a6272be30dd"
    },
    {
        "Name":  "deeperdarker-neoforge-1.21-1.3.4.jar",
        "Path":  "C:\\Users\\nacho\\AppData\\Roaming\\.minecraft\\mods\\deeperdarker-neoforge-1.21-1.3.4.jar",
        "Hash":  "e519bed972f9728af38f351c3dcffc1324e883bf"
    },
    {
        "Name":  "DiagonalFences-v21.1.1-1.21.1-NeoForge.jar",
        "Path":  "C:\\Users\\nacho\\AppData\\Roaming\\.minecraft\\mods\\DiagonalFences-v21.1.1-1.21.1-NeoForge.jar",
        "Hash":  "d77da342ec4fcdea694911cba068e310a0230621"
    },
    {
        "Name":  "DistantHorizons-2.4.5-b-1.21.1.jar",
        "Path":  "C:\\Users\\nacho\\AppData\\Roaming\\.minecraft\\mods\\DistantHorizons-2.4.5-b-1.21.1.jar",
        "Hash":  "2a1243b18ccc117dee0fae5e976a494d8234e8be"
    },
    {
        "Name":  "dummmmmmy-1.21-2.0.11-neoforge.jar",
        "Path":  "C:\\Users\\nacho\\AppData\\Roaming\\.minecraft\\mods\\dummmmmmy-1.21-2.0.11-neoforge.jar",
        "Hash":  "1bdaf699dd40c03c96a85f64ae9b54a8e40bb539"
    },
    {
        "Name":  "dungeons+-1.10.1.jar",
        "Path":  "C:\\Users\\nacho\\AppData\\Roaming\\.minecraft\\mods\\dungeons+-1.10.1.jar",
        "Hash":  "86f4d4cf066ea232c9810d3e7af0b150e41f6fa8"
    },
    {
        "Name":  "DustyDecorations_1.21.1Neoforge_V1.10.3.jar",
        "Path":  "C:\\Users\\nacho\\AppData\\Roaming\\.minecraft\\mods\\DustyDecorations_1.21.1Neoforge_V1.10.3.jar",
        "Hash":  "697e736a38291d0eeb91620b5078a1d5813c878f"
    },
    {
        "Name":  "DyedFlames-v21.1.1-1.21.1-NeoForge.jar",
        "Path":  "C:\\Users\\nacho\\AppData\\Roaming\\.minecraft\\mods\\DyedFlames-v21.1.1-1.21.1-NeoForge.jar",
        "Hash":  "25cea136906ba978c553c2f38016cd7c6af2f0ff"
    },
    {
        "Name":  "EasyAnvils-v21.1.0-1.21.1-NeoForge.jar",
        "Path":  "C:\\Users\\nacho\\AppData\\Roaming\\.minecraft\\mods\\EasyAnvils-v21.1.0-1.21.1-NeoForge.jar",
        "Hash":  "376c02e44dfcb44b79a494b1dba87b2ffb24277f"
    },
    {
        "Name":  "EasyShulkerBoxes-v21.1.3-1.21.1-NeoForge.jar",
        "Path":  "C:\\Users\\nacho\\AppData\\Roaming\\.minecraft\\mods\\EasyShulkerBoxes-v21.1.3-1.21.1-NeoForge.jar",
        "Hash":  "9491302950e20bec758f67f13ff21663ecf40986"
    },
    {
        "Name":  "effectual-neoforge-1.3.1-1.21.1.jar",
        "Path":  "C:\\Users\\nacho\\AppData\\Roaming\\.minecraft\\mods\\effectual-neoforge-1.3.1-1.21.1.jar",
        "Hash":  "99c8fd98d8aa553a6803438b17022cae438fa1bd"
    },
    {
        "Name":  "eg_particle_interactions-0.4.1-neoforge-mc1.21.1.jar",
        "Path":  "C:\\Users\\nacho\\AppData\\Roaming\\.minecraft\\mods\\eg_particle_interactions-0.4.1-neoforge-mc1.21.1.jar",
        "Hash":  "5d851a305cd25dc98593ebe2612c9855b685de97"
    },
    {
        "Name":  "elytraslot-neoforge-9.0.2+1.21.1.jar",
        "Path":  "C:\\Users\\nacho\\AppData\\Roaming\\.minecraft\\mods\\elytraslot-neoforge-9.0.2+1.21.1.jar",
        "Hash":  "8ac6cf959fe66399aa7e86b6e6f933e07d155b7e"
    },
    {
        "Name":  "elytra_physics-neoforge-2.3_mc1.20.5-1.21.1.jar",
        "Path":  "C:\\Users\\nacho\\AppData\\Roaming\\.minecraft\\mods\\elytra_physics-neoforge-2.3_mc1.20.5-1.21.1.jar",
        "Hash":  "16145ad2da3d2e097114601f4303121bcd325829"
    },
    {
        "Name":  "enchanted-vertical-slabs-2.3.2-neoforge-mc1.21.jar",
        "Path":  "C:\\Users\\nacho\\AppData\\Roaming\\.minecraft\\mods\\enchanted-vertical-slabs-2.3.2-neoforge-mc1.21.jar",
        "Hash":  "c79190277ac923f17b025bcfd438f704279cfd0d"
    },
    {
        "Name":  "enchdesc-neoforge-1.21.1-21.1.9.jar",
        "Path":  "C:\\Users\\nacho\\AppData\\Roaming\\.minecraft\\mods\\enchdesc-neoforge-1.21.1-21.1.9.jar",
        "Hash":  "e4fa515c5deab3165f250f2a1297ac836d496064"
    },
    {
        "Name":  "Ender_Cataclysm_1.21.1.jar",
        "Path":  "C:\\Users\\nacho\\AppData\\Roaming\\.minecraft\\mods\\Ender_Cataclysm_1.21.1.jar",
        "Hash":  "33dabb2e3ee9dd2490559e53893d1f1451194160"
    },
    {
        "Name":  "endrem-neoforge-1.21.X-6.0.2.jar",
        "Path":  "C:\\Users\\nacho\\AppData\\Roaming\\.minecraft\\mods\\endrem-neoforge-1.21.X-6.0.2.jar",
        "Hash":  "bfba2c654f3df8cc7d6006056eefbf2b9070dcd4"
    },
    {
        "Name":  "entityculling-neoforge-1.9.4-mc1.21.1.jar",
        "Path":  "C:\\Users\\nacho\\AppData\\Roaming\\.minecraft\\mods\\entityculling-neoforge-1.9.4-mc1.21.1.jar",
        "Hash":  "d265fdd6f8c052873f098b7acd5db7617f6d7bc0"
    },
    {
        "Name":  "entity_model_features_1.21-neoforge-3.0.10.jar",
        "Path":  "C:\\Users\\nacho\\AppData\\Roaming\\.minecraft\\mods\\entity_model_features_1.21-neoforge-3.0.10.jar",
        "Hash":  "558162f7704a324555581db935766d017dbed2ca"
    },
    {
        "Name":  "entity_sound_features_1.21-neoforge-0.7.1.jar",
        "Path":  "C:\\Users\\nacho\\AppData\\Roaming\\.minecraft\\mods\\entity_sound_features_1.21-neoforge-0.7.1.jar",
        "Hash":  "fc9c9ecca9c14aedb0a5a0bec667d1ba6e726b40"
    },
    {
        "Name":  "entity_texture_features_1.21-neoforge-7.0.8.jar",
        "Path":  "C:\\Users\\nacho\\AppData\\Roaming\\.minecraft\\mods\\entity_texture_features_1.21-neoforge-7.0.8.jar",
        "Hash":  "1b9fa548d04b67508a9ad63fe6fb69d6a315232f"
    },
    {
        "Name":  "fallingleaves-1.21.1-2.5.1.jar",
        "Path":  "C:\\Users\\nacho\\AppData\\Roaming\\.minecraft\\mods\\fallingleaves-1.21.1-2.5.1.jar",
        "Hash":  "93f479691d5a88775d90e9fa19e814b7301a363b"
    },
    {
        "Name":  "FarmersDelight-1.21.1-1.2.9.jar",
        "Path":  "C:\\Users\\nacho\\AppData\\Roaming\\.minecraft\\mods\\FarmersDelight-1.21.1-1.2.9.jar",
        "Hash":  "9abe078f48781e4b87288dbc59691c8ba1152d8d"
    },
    {
        "Name":  "FastItemFrames-v21.1.6-1.21.1-NeoForge.jar",
        "Path":  "C:\\Users\\nacho\\AppData\\Roaming\\.minecraft\\mods\\FastItemFrames-v21.1.6-1.21.1-NeoForge.jar",
        "Hash":  "76bf4f0ae0117c86e0d5fda598d459537576ed2e"
    },
    {
        "Name":  "fdbosses-2.0.9-1.21.1.jar",
        "Path":  "C:\\Users\\nacho\\AppData\\Roaming\\.minecraft\\mods\\fdbosses-2.0.9-1.21.1.jar",
        "Hash":  "e25dffb05f9dd157201e9a2eb67ba362aef3ece4"
    },
    {
        "Name":  "fdlib-1.0.5-1.21.1.jar",
        "Path":  "C:\\Users\\nacho\\AppData\\Roaming\\.minecraft\\mods\\fdlib-1.0.5-1.21.1.jar",
        "Hash":  "960ec10a2b2f6b1aba5acbccebca625ccd2a8fdd"
    },
    {
        "Name":  "ferritecore-7.0.2-neoforge.jar",
        "Path":  "C:\\Users\\nacho\\AppData\\Roaming\\.minecraft\\mods\\ferritecore-7.0.2-neoforge.jar",
        "Hash":  "7279fc52c32a033acc2864a9bcb018b2e04bbd03"
    },
    {
        "Name":  "Fog-neoforge-1.11.0-1.21.1.jar",
        "Path":  "C:\\Users\\nacho\\AppData\\Roaming\\.minecraft\\mods\\Fog-neoforge-1.11.0-1.21.1.jar",
        "Hash":  "106460aa8b09e8ce6051b332d104c787c208d28a"
    },
    {
        "Name":  "ForgeConfigAPIPort-v21.1.6-1.21.1-NeoForge.jar",
        "Path":  "C:\\Users\\nacho\\AppData\\Roaming\\.minecraft\\mods\\ForgeConfigAPIPort-v21.1.6-1.21.1-NeoForge.jar",
        "Hash":  "14f2dd9f43254b8c06af04b6f0c8ae5192f658b5"
    },
    {
        "Name":  "forgematica-0.4.1+mc1.21.1.jar",
        "Path":  "C:\\Users\\nacho\\AppData\\Roaming\\.minecraft\\mods\\forgematica-0.4.1+mc1.21.1.jar",
        "Hash":  "5ef9d8fd67791217a10f3243ed66764e254cd470"
    },
    {
        "Name":  "formations-1.0.4-neoforge-mc1.21.jar",
        "Path":  "C:\\Users\\nacho\\AppData\\Roaming\\.minecraft\\mods\\formations-1.0.4-neoforge-mc1.21.jar",
        "Hash":  "3845f96c9304f6956688f7a35205e9354bf411b0"
    },
    {
        "Name":  "formationsnether-1.0.5-mc1.21+.jar",
        "Path":  "C:\\Users\\nacho\\AppData\\Roaming\\.minecraft\\mods\\formationsnether-1.0.5-mc1.21+.jar",
        "Hash":  "12b69c1cd22bbbe8c5888a030bef791b992b0d39"
    },
    {
        "Name":  "formationsoverworld-1.0.5-mc1.21+.jar",
        "Path":  "C:\\Users\\nacho\\AppData\\Roaming\\.minecraft\\mods\\formationsoverworld-1.0.5-mc1.21+.jar",
        "Hash":  "edbc169c78f9f1cdf5233e996f12b21e7e1cdf18"
    },
    {
        "Name":  "friendsandfoes-neoforge-4.0.17+mc1.21.1.jar",
        "Path":  "C:\\Users\\nacho\\AppData\\Roaming\\.minecraft\\mods\\friendsandfoes-neoforge-4.0.17+mc1.21.1.jar",
        "Hash":  "b9d6173e73db9e6df3025a46e91cb480cb771b6f"
    },
    {
        "Name":  "frightsdelight-neoforge-1.21.1-1.4.1.jar",
        "Path":  "C:\\Users\\nacho\\AppData\\Roaming\\.minecraft\\mods\\frightsdelight-neoforge-1.21.1-1.4.1.jar",
        "Hash":  "cce01f9012d8a801c52e38bef2da57f074f082de"
    },
    {
        "Name":  "fzzy_config-0.7.5+1.21+neoforge.jar",
        "Path":  "C:\\Users\\nacho\\AppData\\Roaming\\.minecraft\\mods\\fzzy_config-0.7.5+1.21+neoforge.jar",
        "Hash":  "81b9e4796cc40a04a6fa0cdf2682b326de726133"
    },
    {
        "Name":  "geckolib-neoforge-1.21.1-4.8.2.jar",
        "Path":  "C:\\Users\\nacho\\AppData\\Roaming\\.minecraft\\mods\\geckolib-neoforge-1.21.1-4.8.2.jar",
        "Hash":  "b2d84a5ea8b8944be66dbf817f0d4aa3f494db7a"
    },
    {
        "Name":  "gliders-1.21.1-neoforge-1.1.8.jar",
        "Path":  "C:\\Users\\nacho\\AppData\\Roaming\\.minecraft\\mods\\gliders-1.21.1-neoforge-1.1.8.jar",
        "Hash":  "f68e8fa4fb1a126cfb660df32fb009b2cc900c6b"
    },
    {
        "Name":  "GPUTape-1.20.6-1.21x-1.0.3.jar",
        "Path":  "C:\\Users\\nacho\\AppData\\Roaming\\.minecraft\\mods\\GPUTape-1.20.6-1.21x-1.0.3.jar",
        "Hash":  "96d8f1df0f08e169396b603c42cf997e9081de59"
    },
    {
        "Name":  "grieflogger-1.2.9-1.21.1-neoforge.jar",
        "Path":  "C:\\Users\\nacho\\AppData\\Roaming\\.minecraft\\mods\\grieflogger-1.2.9-1.21.1-neoforge.jar",
        "Hash":  "db3c302c407a38bf921728d8150163535a04e8f2"
    },
    {
        "Name":  "Hearths v1.0.5.mod.jar",
        "Path":  "C:\\Users\\nacho\\AppData\\Roaming\\.minecraft\\mods\\Hearths v1.0.5.mod.jar",
        "Hash":  "7d1d4be3c3033b7df902b51915f37f53d60718b5"
    },
    {
        "Name":  "holdmyitemsnf-1.21.1v2.1.jar",
        "Path":  "C:\\Users\\nacho\\AppData\\Roaming\\.minecraft\\mods\\holdmyitemsnf-1.21.1v2.1.jar",
        "Hash":  "c4a8d9c03c659c696d63580e9b71e7a7c64dae33"
    },
    {
        "Name":  "HopoBetterRuinedPortals-[1.21.1-1.21.3]-1.4.4b.jar",
        "Path":  "C:\\Users\\nacho\\AppData\\Roaming\\.minecraft\\mods\\HopoBetterRuinedPortals-[1.21.1-1.21.3]-1.4.4b.jar",
        "Hash":  "c4a8d9c03c659c696d63580e9b71e7a7c64dae33"
    },
    {
        "Name":  "HopoBetterUnderwaterRuins-[1.21.1-1.21.3]-1.2.1b.jar",
        "Path":  "C:\\Users\\nacho\\AppData\\Roaming\\.minecraft\\mods\\HopoBetterUnderwaterRuins-[1.21.1-1.21.3]-1.2.1b.jar",
        "Hash":  "c4a8d9c03c659c696d63580e9b71e7a7c64dae33"
    },
    {
        "Name":  "Iceberg-1.21.1-neoforge-1.3.2.jar",
        "Path":  "C:\\Users\\nacho\\AppData\\Roaming\\.minecraft\\mods\\Iceberg-1.21.1-neoforge-1.3.2.jar",
        "Hash":  "f6014d198be9503573cd9cb41cc789d282768ad8"
    },
    {
        "Name":  "ImmediatelyFast-NeoForge-1.6.9+1.21.1.jar",
        "Path":  "C:\\Users\\nacho\\AppData\\Roaming\\.minecraft\\mods\\ImmediatelyFast-NeoForge-1.6.9+1.21.1.jar",
        "Hash":  "01df8113ce41993ea341b973afc36ef2e1701e00"
    },
    {
        "Name":  "immersivelanterns-neoforge-1.0.6-1.21.1.jar",
        "Path":  "C:\\Users\\nacho\\AppData\\Roaming\\.minecraft\\mods\\immersivelanterns-neoforge-1.0.6-1.21.1.jar",
        "Hash":  "5315b3323b83130123f69b1b3bfc777376e4961f"
    },
    {
        "Name":  "ImmersiveUI-NEOFORGE-0.3.3+1.21.1.jar",
        "Path":  "C:\\Users\\nacho\\AppData\\Roaming\\.minecraft\\mods\\ImmersiveUI-NEOFORGE-0.3.3+1.21.1.jar",
        "Hash":  "5e9dda03c6142400b95dc3114675e07c943d554d"
    },
    {
        "Name":  "immersive_melodies-neoforge-0.6.2+1.21.1.jar",
        "Path":  "C:\\Users\\nacho\\AppData\\Roaming\\.minecraft\\mods\\immersive_melodies-neoforge-0.6.2+1.21.1.jar",
        "Hash":  "b854ee1c181eb1da9cd9999aa656b3bbcee29c1e"
    },
    {
        "Name":  "inventorio-mc1.21.1-neoforge-v1.11.0.jar",
        "Path":  "C:\\Users\\nacho\\AppData\\Roaming\\.minecraft\\mods\\inventorio-mc1.21.1-neoforge-v1.11.0.jar",
        "Hash":  "9baf305354ec0430680d0eaf6f24ee7f54631d3f"
    },
    {
        "Name":  "Inventory Management Deluxe-1.21.1-NeoForge-1.0.3.jar",
        "Path":  "C:\\Users\\nacho\\AppData\\Roaming\\.minecraft\\mods\\Inventory Management Deluxe-1.21.1-NeoForge-1.0.3.jar",
        "Hash":  "da6b2b5b111fd752601a5ef19a489fcf42c7ff8f"
    },
    {
        "Name":  "InventoryInteractions-1.0.0+1.21.1+neoforge.jar",
        "Path":  "C:\\Users\\nacho\\AppData\\Roaming\\.minecraft\\mods\\InventoryInteractions-1.0.0+1.21.1+neoforge.jar",
        "Hash":  "fee1ea31e89075b4d1a1242e5045736ce94fc836"
    },
    {
        "Name":  "InventoryParticles-1.3.2+1.21.1+neoforge.jar",
        "Path":  "C:\\Users\\nacho\\AppData\\Roaming\\.minecraft\\mods\\InventoryParticles-1.3.2+1.21.1+neoforge.jar",
        "Hash":  "7a351d8cc9dd84a3a26bd226a8265bcde89ae60a"
    },
    {
        "Name":  "iris-neoforge-1.8.12+mc1.21.1.jar",
        "Path":  "C:\\Users\\nacho\\AppData\\Roaming\\.minecraft\\mods\\iris-neoforge-1.8.12+mc1.21.1.jar",
        "Hash":  "a3e6355915c7d3b2bc392724795113e51d289378"
    },
    {
        "Name":  "jeed-1.21-2.3.2.jar",
        "Path":  "C:\\Users\\nacho\\AppData\\Roaming\\.minecraft\\mods\\jeed-1.21-2.3.2.jar",
        "Hash":  "144ffaf459b58db14614a7e1ef3425c2594e30b6"
    },
    {
        "Name":  "jei-1.21.1-neoforge-19.27.0.340.jar",
        "Path":  "C:\\Users\\nacho\\AppData\\Roaming\\.minecraft\\mods\\jei-1.21.1-neoforge-19.27.0.340.jar",
        "Hash":  "27d0d85e7e32e926fc3664ab6815df5cdabb7941"
    },
    {
        "Name":  "keep-some-inventory-v2.0.1.jar",
        "Path":  "C:\\Users\\nacho\\AppData\\Roaming\\.minecraft\\mods\\keep-some-inventory-v2.0.1.jar",
        "Hash":  "1e3644f4532d053ff86ed3865c90726011a182f8"
    },
    {
        "Name":  "kotlinforforge-5.11.0-all.jar",
        "Path":  "C:\\Users\\nacho\\AppData\\Roaming\\.minecraft\\mods\\kotlinforforge-5.11.0-all.jar",
        "Hash":  "4d83e8a8e8cb06b306d2cea1e903680fe513f1f3"
    },
    {
        "Name":  "kubejs-neoforge-2101.7.2-build.348.jar",
        "Path":  "C:\\Users\\nacho\\AppData\\Roaming\\.minecraft\\mods\\kubejs-neoforge-2101.7.2-build.348.jar",
        "Hash":  "d3b606167d77dd3c561e682b7e373a01a369cc95"
    },
    {
        "Name":  "kubejsdelight-1.1.4.jar",
        "Path":  "C:\\Users\\nacho\\AppData\\Roaming\\.minecraft\\mods\\kubejsdelight-1.1.4.jar",
        "Hash":  "29e538714cf1b0506e9caeb515563775357b2a9c"
    },
    {
        "Name":  "leafmealone-1.1.0.jar",
        "Path":  "C:\\Users\\nacho\\AppData\\Roaming\\.minecraft\\mods\\leafmealone-1.1.0.jar",
        "Hash":  "809bbf3a36a15916f66997ad09df6130c6f63e5a"
    },
    {
        "Name":  "LeaveMyBarsAlone-v21.1.2-1.21.1-NeoForge.jar",
        "Path":  "C:\\Users\\nacho\\AppData\\Roaming\\.minecraft\\mods\\LeaveMyBarsAlone-v21.1.2-1.21.1-NeoForge.jar",
        "Hash":  "7156b542431ea057539070c0c00feb8c9f58c099"
    },
    {
        "Name":  "lionfishapi-2.6.jar",
        "Path":  "C:\\Users\\nacho\\AppData\\Roaming\\.minecraft\\mods\\lionfishapi-2.6.jar",
        "Hash":  "3d9059ea05839e0daab926848d91ecb14ca5a4d4"
    },
    {
        "Name":  "lithium-neoforge-0.15.1+mc1.21.1.jar",
        "Path":  "C:\\Users\\nacho\\AppData\\Roaming\\.minecraft\\mods\\lithium-neoforge-0.15.1+mc1.21.1.jar",
        "Hash":  "38295e15a600899697a5dbd29b1e9c15060e5760"
    },
    {
        "Name":  "lithostitched-1.5.4-neoforge-1.21.1.jar",
        "Path":  "C:\\Users\\nacho\\AppData\\Roaming\\.minecraft\\mods\\lithostitched-1.5.4-neoforge-1.21.1.jar",
        "Hash":  "dc71515ddec9b2788f30ae7da490ef4a727fa45a"
    },
    {
        "Name":  "lootjs-neoforge-1.21.1-3.6.1.jar",
        "Path":  "C:\\Users\\nacho\\AppData\\Roaming\\.minecraft\\mods\\lootjs-neoforge-1.21.1-3.6.1.jar",
        "Hash":  "a5b8019795de70fde065dc938bf4750aacf9f935"
    },
    {
        "Name":  "luckyswardrobe-2.0.0.jar",
        "Path":  "C:\\Users\\nacho\\AppData\\Roaming\\.minecraft\\mods\\luckyswardrobe-2.0.0.jar",
        "Hash":  "a0a37d721fa30e499e945af5782e1e1e83c70427"
    },
    {
        "Name":  "mafglib-0.4.1+mc1.21.1.jar",
        "Path":  "C:\\Users\\nacho\\AppData\\Roaming\\.minecraft\\mods\\mafglib-0.4.1+mc1.21.1.jar",
        "Hash":  "043e9c2dc77620c32da268f6e631d664e7582255"
    },
    {
        "Name":  "mixintracereforged-neoforge-1.0.0-1.21.1.jar",
        "Path":  "C:\\Users\\nacho\\AppData\\Roaming\\.minecraft\\mods\\mixintracereforged-neoforge-1.0.0-1.21.1.jar",
        "Hash":  "7184298a588d58d95ba18fb37d71809cf3b47cfb"
    },
    {
        "Name":  "mobs_of_mythology-neoforge-1.21.1-2.2.2.jar",
        "Path":  "C:\\Users\\nacho\\AppData\\Roaming\\.minecraft\\mods\\mobs_of_mythology-neoforge-1.21.1-2.2.2.jar",
        "Hash":  "6f9065389c94c272b734a7a3b92222efac72f644"
    },
    {
        "Name":  "modernfix-neoforge-5.25.1+mc1.21.1.jar",
        "Path":  "C:\\Users\\nacho\\AppData\\Roaming\\.minecraft\\mods\\modernfix-neoforge-5.25.1+mc1.21.1.jar",
        "Hash":  "5407ee2d311f6f16773292fe22942a023a19677d"
    },
    {
        "Name":  "moonlight-1.21-2.28.2-neoforge.jar",
        "Path":  "C:\\Users\\nacho\\AppData\\Roaming\\.minecraft\\mods\\moonlight-1.21-2.28.2-neoforge.jar",
        "Hash":  "100339839fce7009fa646562cd9ae0438c64cb1c"
    },
    {
        "Name":  "morejs-neoforge-1.21.1-0.16.0.jar",
        "Path":  "C:\\Users\\nacho\\AppData\\Roaming\\.minecraft\\mods\\morejs-neoforge-1.21.1-0.16.0.jar",
        "Hash":  "7e8aea4f03b18076cab5555f6d30e35ff919b342"
    },
    {
        "Name":  "MossyLib-1.1.0+1.21.1+neoforge.jar",
        "Path":  "C:\\Users\\nacho\\AppData\\Roaming\\.minecraft\\mods\\MossyLib-1.1.0+1.21.1+neoforge.jar",
        "Hash":  "ce2e56fbb98f7bc9c937a95ab3789d5b2c07c948"
    },
    {
        "Name":  "mowziesmobs-1.21.1-1.7.5.jar",
        "Path":  "C:\\Users\\nacho\\AppData\\Roaming\\.minecraft\\mods\\mowziesmobs-1.21.1-1.7.5.jar",
        "Hash":  "f462b46d4bd3071708cebd4b06c16857ad593e22"
    },
    {
        "Name":  "mru-1.0.19+LTS+1.21.1+neoforge.jar",
        "Path":  "C:\\Users\\nacho\\AppData\\Roaming\\.minecraft\\mods\\mru-1.0.19+LTS+1.21.1+neoforge.jar",
        "Hash":  "903f41bce1ff0b4bd13b66d46bfbd21423663bbc"
    },
    {
        "Name":  "MyNethersDelight-1.21.1-1.9.jar",
        "Path":  "C:\\Users\\nacho\\AppData\\Roaming\\.minecraft\\mods\\MyNethersDelight-1.21.1-1.9.jar",
        "Hash":  "146bc38650e09875c678a78014a3ed55d2fd4ca9"
    },
    {
        "Name":  "NBTac-NEOFORGE-1.21.1-1.3.10.jar",
        "Path":  "C:\\Users\\nacho\\AppData\\Roaming\\.minecraft\\mods\\NBTac-NEOFORGE-1.21.1-1.3.10.jar",
        "Hash":  "1cf9b213218103d6a1249b5db49b42fc389fb7dd"
    },
    {
        "Name":  "netherportalfix-neoforge-1.21.1-21.1.1.jar",
        "Path":  "C:\\Users\\nacho\\AppData\\Roaming\\.minecraft\\mods\\netherportalfix-neoforge-1.21.1-21.1.1.jar",
        "Hash":  "9f1ba483216aebce1ee6185601231158684f5de8"
    },
    {
        "Name":  "no-telemetry-1.10.0.jar",
        "Path":  "C:\\Users\\nacho\\AppData\\Roaming\\.minecraft\\mods\\no-telemetry-1.10.0.jar",
        "Hash":  "3d52342f5825d01dda6661ef7116cdbacbe49746"
    },
    {
        "Name":  "NoChatReports-NEOFORGE-1.21.1-v2.9.1.jar",
        "Path":  "C:\\Users\\nacho\\AppData\\Roaming\\.minecraft\\mods\\NoChatReports-NEOFORGE-1.21.1-v2.9.1.jar",
        "Hash":  "9edfc7861277ff661141304dc8216f83eacdd9af"
    },
    {
        "Name":  "noisium-neoforge-2.3.0+mc1.21-1.21.1.jar",
        "Path":  "C:\\Users\\nacho\\AppData\\Roaming\\.minecraft\\mods\\noisium-neoforge-2.3.0+mc1.21-1.21.1.jar",
        "Hash":  "1bea6b61378ba80f038256c4345d9ff3b67928c4"
    },
    {
        "Name":  "Not Enough Recipe Book-NEOFORGE-0.4.3+1.21.jar",
        "Path":  "C:\\Users\\nacho\\AppData\\Roaming\\.minecraft\\mods\\Not Enough Recipe Book-NEOFORGE-0.4.3+1.21.jar",
        "Hash":  "e0c36cd85d3d31cc2afb1bfc6b885f505245252f"
    },
    {
        "Name":  "notenoughanimations-neoforge-1.11.1-mc1.21.1.jar",
        "Path":  "C:\\Users\\nacho\\AppData\\Roaming\\.minecraft\\mods\\notenoughanimations-neoforge-1.11.1-mc1.21.1.jar",
        "Hash":  "77bc4502a329cf664c28ea21d3abccad26dfca50"
    },
    {
        "Name":  "notenoughcrashes-neoforge-4.4.9+1.21.1.jar",
        "Path":  "C:\\Users\\nacho\\AppData\\Roaming\\.minecraft\\mods\\notenoughcrashes-neoforge-4.4.9+1.21.1.jar",
        "Hash":  "4108c653e3e0d54a6df3c5354a752ea0ea801ffe"
    },
    {
        "Name":  "OctoLib-NEOFORGE-0.6.0.4+1.21.jar",
        "Path":  "C:\\Users\\nacho\\AppData\\Roaming\\.minecraft\\mods\\OctoLib-NEOFORGE-0.6.0.4+1.21.jar",
        "Hash":  "106ca4d0a3597e1a5c6489e98361c81436c528e0"
    },
    {
        "Name":  "OverflowingBars-v21.1.1-1.21.1-NeoForge.jar",
        "Path":  "C:\\Users\\nacho\\AppData\\Roaming\\.minecraft\\mods\\OverflowingBars-v21.1.1-1.21.1-NeoForge.jar",
        "Hash":  "a9dea4b9ef893fc955512ff2dee75c9c82e09a52"
    },
    {
        "Name":  "owo-lib-neoforge-0.12.15.5-beta.1+1.21.jar",
        "Path":  "C:\\Users\\nacho\\AppData\\Roaming\\.minecraft\\mods\\owo-lib-neoforge-0.12.15.5-beta.1+1.21.jar",
        "Hash":  "48dda11a6710591cf162bdbedf982ea21dd1f2ed"
    },
    {
        "Name":  "packed_packs-neoforge-2.0.3+1.21.1.jar",
        "Path":  "C:\\Users\\nacho\\AppData\\Roaming\\.minecraft\\mods\\packed_packs-neoforge-2.0.3+1.21.1.jar",
        "Hash":  "6f2e26b87420d3ab15a199aa0156c2c19511edc6"
    },
    {
        "Name":  "ParticleEffects-1.2.0+1.21.1+neoforge.jar",
        "Path":  "C:\\Users\\nacho\\AppData\\Roaming\\.minecraft\\mods\\ParticleEffects-1.2.0+1.21.1+neoforge.jar",
        "Hash":  "c25e8a75900521762ab077b3821335c1a1ad0708"
    },
    {
        "Name":  "particlerain-4.0.0-beta.5+1.21.1-neoforge.jar",
        "Path":  "C:\\Users\\nacho\\AppData\\Roaming\\.minecraft\\mods\\particlerain-4.0.0-beta.5+1.21.1-neoforge.jar",
        "Hash":  "be3ffc30f87963c21fc43827931cde33a3439590"
    },
    {
        "Name":  "particle_core-0.3.1-fix1+1.21+neoforge.jar",
        "Path":  "C:\\Users\\nacho\\AppData\\Roaming\\.minecraft\\mods\\particle_core-0.3.1-fix1+1.21+neoforge.jar",
        "Hash":  "75801cd0ccc7454c08e38e2138f215515e0d9b1f"
    },
    {
        "Name":  "particular-1.21.1-NeoForge-1.1.7.jar",
        "Path":  "C:\\Users\\nacho\\AppData\\Roaming\\.minecraft\\mods\\particular-1.21.1-NeoForge-1.1.7.jar",
        "Hash":  "39d2fa3c396bf75a00078922dd6c2a7bf9f63f46"
    },
    {
        "Name":  "piglinproliferation-1.21.1-2.0.12.jar",
        "Path":  "C:\\Users\\nacho\\AppData\\Roaming\\.minecraft\\mods\\piglinproliferation-1.21.1-2.0.12.jar",
        "Hash":  "0851801cc4faa05838bb1fc1b61439ad8d525316"
    },
    {
        "Name":  "platform-neoforge-1.21.1-1.2.11.3.jar",
        "Path":  "C:\\Users\\nacho\\AppData\\Roaming\\.minecraft\\mods\\platform-neoforge-1.21.1-1.2.11.3.jar",
        "Hash":  "abd9437448d930c62871fd214ff37a3a6c74da60"
    },
    {
        "Name":  "polytone-1.21-3.6.4-neoforge.jar",
        "Path":  "C:\\Users\\nacho\\AppData\\Roaming\\.minecraft\\mods\\polytone-1.21-3.6.4-neoforge.jar",
        "Hash":  "876d3b6e6ce69782149e73dac6c61c98be2e2485"
    },
    {
        "Name":  "prickle-neoforge-1.21.1-21.1.11.jar",
        "Path":  "C:\\Users\\nacho\\AppData\\Roaming\\.minecraft\\mods\\prickle-neoforge-1.21.1-21.1.11.jar",
        "Hash":  "5174059ecf97340a0de5ef211b938de26c4eaa36"
    },
    {
        "Name":  "Prism-1.21.1-neoforge-1.0.11.jar",
        "Path":  "C:\\Users\\nacho\\AppData\\Roaming\\.minecraft\\mods\\Prism-1.21.1-neoforge-1.0.11.jar",
        "Hash":  "1ae6f7be2ba8f963344dbf27e552920a7bc7a35f"
    },
    {
        "Name":  "PuzzlesLib-v21.1.39-1.21.1-NeoForge.jar",
        "Path":  "C:\\Users\\nacho\\AppData\\Roaming\\.minecraft\\mods\\PuzzlesLib-v21.1.39-1.21.1-NeoForge.jar",
        "Hash":  "bcc0900fbbf6d6fc5ca05039cd5725e6145225f2"
    },
    {
        "Name":  "qraftyfied-9.1.1.jar",
        "Path":  "C:\\Users\\nacho\\AppData\\Roaming\\.minecraft\\mods\\qraftyfied-9.1.1.jar",
        "Hash":  "c9f9b9873888dc480b2046365ad6ffaf083fe8f2"
    },
    {
        "Name":  "quality_food-1.21.1-2.2.5.jar",
        "Path":  "C:\\Users\\nacho\\AppData\\Roaming\\.minecraft\\mods\\quality_food-1.21.1-2.2.5.jar",
        "Hash":  "2662be0342d1c9b32203f2638c1804c8a13a9ac0"
    },
    {
        "Name":  "reeses-sodium-options-neoforge-1.8.3+mc1.21.4.jar",
        "Path":  "C:\\Users\\nacho\\AppData\\Roaming\\.minecraft\\mods\\reeses-sodium-options-neoforge-1.8.3+mc1.21.4.jar",
        "Hash":  "b03d05495be28d8cef7a34872941bb8d703d60e6"
    },
    {
        "Name":  "reflex-neoforge-1.0.4+mc1.21.1.jar",
        "Path":  "C:\\Users\\nacho\\AppData\\Roaming\\.minecraft\\mods\\reflex-neoforge-1.0.4+mc1.21.1.jar",
        "Hash":  "14606a7a012b4326099a01485bb6b425df483ed5"
    },
    {
        "Name":  "resourcefulconfig-neoforge-1.21-3.0.11.jar",
        "Path":  "C:\\Users\\nacho\\AppData\\Roaming\\.minecraft\\mods\\resourcefulconfig-neoforge-1.21-3.0.11.jar",
        "Hash":  "6bf2b6ea9c071c00a2abcdc552667fb6f7d21031"
    },
    {
        "Name":  "resourcefullib-neoforge-1.21-3.0.12.jar",
        "Path":  "C:\\Users\\nacho\\AppData\\Roaming\\.minecraft\\mods\\resourcefullib-neoforge-1.21-3.0.12.jar",
        "Hash":  "24389c8e48ff0e8594e4686b750c494c66a5f8df"
    },
    {
        "Name":  "Resourceloader-2.3.jar",
        "Path":  "C:\\Users\\nacho\\AppData\\Roaming\\.minecraft\\mods\\Resourceloader-2.3.jar",
        "Hash":  "605883336322c7bc539311d819875c6c15185a22"
    },
    {
        "Name":  "rhino-2101.2.7-build.81.jar",
        "Path":  "C:\\Users\\nacho\\AppData\\Roaming\\.minecraft\\mods\\rhino-2101.2.7-build.81.jar",
        "Hash":  "480235a9f7749f68ce6fec3b9c3cac3428b92a4a"
    },
    {
        "Name":  "Ribbits-1.21.1-NeoForge-4.1.4.jar",
        "Path":  "C:\\Users\\nacho\\AppData\\Roaming\\.minecraft\\mods\\Ribbits-1.21.1-NeoForge-4.1.4.jar",
        "Hash":  "1ad756c32ed77a150e9c699884f59b1020dab721"
    },
    {
        "Name":  "rusticdelight-neoforge-1.21-1.5.1.jar",
        "Path":  "C:\\Users\\nacho\\AppData\\Roaming\\.minecraft\\mods\\rusticdelight-neoforge-1.21-1.5.1.jar",
        "Hash":  "4239b6c80f759ef9356e484bcf3950a2a699a046"
    },
    {
        "Name":  "Searchables-neoforge-1.21.1-1.0.2.jar",
        "Path":  "C:\\Users\\nacho\\AppData\\Roaming\\.minecraft\\mods\\Searchables-neoforge-1.21.1-1.0.2.jar",
        "Hash":  "5b8a0b43a474c066371b2e16f9bfb88622552a74"
    },
    {
        "Name":  "SmartBrainLib-neoforge-1.21.1-1.16.11.jar",
        "Path":  "C:\\Users\\nacho\\AppData\\Roaming\\.minecraft\\mods\\SmartBrainLib-neoforge-1.21.1-1.16.11.jar",
        "Hash":  "0310135a01eeceefbc7f1ab017498a65f3ad6836"
    },
    {
        "Name":  "smoothgui-neoforge-1.21.1-1.1.0.jar",
        "Path":  "C:\\Users\\nacho\\AppData\\Roaming\\.minecraft\\mods\\smoothgui-neoforge-1.21.1-1.1.0.jar",
        "Hash":  "7f92bfc79f754b68855770610ad79a3934703c25"
    },
    {
        "Name":  "smoothscrolling-1.21.1-NeoForge-1.0.1.jar",
        "Path":  "C:\\Users\\nacho\\AppData\\Roaming\\.minecraft\\mods\\smoothscrolling-1.21.1-NeoForge-1.0.1.jar",
        "Hash":  "c57b50860de3cc5fbf7aa835dc8fe44bfef7b030"
    },
    {
        "Name":  "sodium-neoforge-0.6.13+mc1.21.1.jar",
        "Path":  "C:\\Users\\nacho\\AppData\\Roaming\\.minecraft\\mods\\sodium-neoforge-0.6.13+mc1.21.1.jar",
        "Hash":  "38af70fa4dc4b2aaac636e92fdba3bedd5a025e1"
    },
    {
        "Name":  "sodiumdynamiclights-neoforge-1.0.10-1.21.1.jar",
        "Path":  "C:\\Users\\nacho\\AppData\\Roaming\\.minecraft\\mods\\sodiumdynamiclights-neoforge-1.0.10-1.21.1.jar",
        "Hash":  "02e9bc7ba28147cdf2d608ecf4f2c1eab34b4652"
    },
    {
        "Name":  "sodiumoptionsapi-neoforge-1.0.10-1.21.1.jar",
        "Path":  "C:\\Users\\nacho\\AppData\\Roaming\\.minecraft\\mods\\sodiumoptionsapi-neoforge-1.0.10-1.21.1.jar",
        "Hash":  "5d014d031fa77ab600e07835b032ef4dcb79b442"
    },
    {
        "Name":  "sootychimneys-neoforge-1.3.3.jar",
        "Path":  "C:\\Users\\nacho\\AppData\\Roaming\\.minecraft\\mods\\sootychimneys-neoforge-1.3.3.jar",
        "Hash":  "e3439125c1e10d08dd7a53152f21cc5028dda102"
    },
    {
        "Name":  "spawn-animations-compats-13.0.jar",
        "Path":  "C:\\Users\\nacho\\AppData\\Roaming\\.minecraft\\mods\\spawn-animations-compats-13.0.jar",
        "Hash":  "cffb38936778e7619eebb217d26c372bc1ce2e00"
    },
    {
        "Name":  "spawnanimations-v1.11.3-mc1.17-1.21.11-mod.jar",
        "Path":  "C:\\Users\\nacho\\AppData\\Roaming\\.minecraft\\mods\\spawnanimations-v1.11.3-mc1.17-1.21.11-mod.jar",
        "Hash":  "d8d38a01b2e46db2dfd393a946bb02a31edbcd7c"
    },
    {
        "Name":  "starcatcher-2.1.2-NEOFORGE-1.21.1.jar",
        "Path":  "C:\\Users\\nacho\\AppData\\Roaming\\.minecraft\\mods\\starcatcher-2.1.2-NEOFORGE-1.21.1.jar",
        "Hash":  "e5417be0723276af795134902228fcbfe897dca4"
    },
    {
        "Name":  "statuseffectbars-1.21.1-NeoForge-1.0.2.jar",
        "Path":  "C:\\Users\\nacho\\AppData\\Roaming\\.minecraft\\mods\\statuseffectbars-1.21.1-NeoForge-1.0.2.jar",
        "Hash":  "bc2d624a831126bb00032d53ca0211d026e95682"
    },
    {
        "Name":  "storagedelight-25.12.09-1.21-neoforge.jar",
        "Path":  "C:\\Users\\nacho\\AppData\\Roaming\\.minecraft\\mods\\storagedelight-25.12.09-1.21-neoforge.jar",
        "Hash":  "b61e8454f99d4e18730ac3e2a2c51c618c4c548a"
    },
    {
        "Name":  "structure_layout_optimizer-neoforge-1.0.11.jar",
        "Path":  "C:\\Users\\nacho\\AppData\\Roaming\\.minecraft\\mods\\structure_layout_optimizer-neoforge-1.0.11.jar",
        "Hash":  "5f0ee1873c64317ca50011860d5de1adba148611"
    },
    {
        "Name":  "SubtleEffects-neoforge-1.21.1-1.13.2-hotfix.1.jar",
        "Path":  "C:\\Users\\nacho\\AppData\\Roaming\\.minecraft\\mods\\SubtleEffects-neoforge-1.21.1-1.13.2-hotfix.1.jar",
        "Hash":  "e80e1e6ba406e435412f81d918442f0ea2da8516"
    },
    {
        "Name":  "supermartijn642configlib-1.1.8-neoforge-mc1.21.jar",
        "Path":  "C:\\Users\\nacho\\AppData\\Roaming\\.minecraft\\mods\\supermartijn642configlib-1.1.8-neoforge-mc1.21.jar",
        "Hash":  "07452242e389975e8a88b97066f4bae6a4ebe574"
    },
    {
        "Name":  "supplementaries-1.21-3.5.13-neoforge.jar",
        "Path":  "C:\\Users\\nacho\\AppData\\Roaming\\.minecraft\\mods\\supplementaries-1.21-3.5.13-neoforge.jar",
        "Hash":  "1527988261097fffa993cc10ef7da4edb50043ef"
    },
    {
        "Name":  "swashbucklers! 2.6.6C 1.21.1 neoforge.jar",
        "Path":  "C:\\Users\\nacho\\AppData\\Roaming\\.minecraft\\mods\\swashbucklers! 2.6.6C 1.21.1 neoforge.jar",
        "Hash":  "cf0f8176110a2ec14ed552ecab8890f78d4e6889"
    },
    {
        "Name":  "tlib-neoforge-1.4.1-1.21.1.jar",
        "Path":  "C:\\Users\\nacho\\AppData\\Roaming\\.minecraft\\mods\\tlib-neoforge-1.4.1-1.21.1.jar",
        "Hash":  "185ae293beab9e810cc3bea29797ee45f784922b"
    },
    {
        "Name":  "toolbar-sounds-v1.1.jar",
        "Path":  "C:\\Users\\nacho\\AppData\\Roaming\\.minecraft\\mods\\toolbar-sounds-v1.1.jar",
        "Hash":  "a074105235c6ce411d2b7b13ef2d9bcd94bc67c5"
    },
    {
        "Name":  "tooltipoverhaul-neoforge-1.21.1-1.4.1.jar",
        "Path":  "C:\\Users\\nacho\\AppData\\Roaming\\.minecraft\\mods\\tooltipoverhaul-neoforge-1.21.1-1.4.1.jar",
        "Hash":  "187fdf157bbb54ecf2c15b05e0215d2f70a44ae3"
    },
    {
        "Name":  "trailandtales_delight-0.4.jar",
        "Path":  "C:\\Users\\nacho\\AppData\\Roaming\\.minecraft\\mods\\trailandtales_delight-0.4.jar",
        "Hash":  "8801b16d3f32a4ab0d317c365351842a0a700dfa"
    },
    {
        "Name":  "tt20-0.7.2.jar",
        "Path":  "C:\\Users\\nacho\\AppData\\Roaming\\.minecraft\\mods\\tt20-0.7.2.jar",
        "Hash":  "62478e85f83c49f5b243d3a646b084debd16f6e2"
    },
    {
        "Name":  "txnilib-neoforge-1.0.24-1.21.1.jar",
        "Path":  "C:\\Users\\nacho\\AppData\\Roaming\\.minecraft\\mods\\txnilib-neoforge-1.0.24-1.21.1.jar",
        "Hash":  "17b1bbb96e922e683a1807a2e7bece603fdc491d"
    },
    {
        "Name":  "uilib-1.0.1-1.21.1-neoforge.jar",
        "Path":  "C:\\Users\\nacho\\AppData\\Roaming\\.minecraft\\mods\\uilib-1.0.1-1.21.1-neoforge.jar",
        "Hash":  "cb0b3adfb3d62cbc839fa29ffb51bdd1fcf30dbf"
    },
    {
        "Name":  "upgrade_aquatic-1.21.1-7.0.1.jar",
        "Path":  "C:\\Users\\nacho\\AppData\\Roaming\\.minecraft\\mods\\upgrade_aquatic-1.21.1-7.0.1.jar",
        "Hash":  "439a90a9eb660822af3ec0fc7af8d3770bbc40af"
    },
    {
        "Name":  "vanillabackport-neoforge-1.21.1-1.1.5.1.jar",
        "Path":  "C:\\Users\\nacho\\AppData\\Roaming\\.minecraft\\mods\\vanillabackport-neoforge-1.21.1-1.1.5.1.jar",
        "Hash":  "0a932acc8d15e32c727fb61f99cabef7bfe63c1f"
    },
    {
        "Name":  "variantsandventures-neoforge-1.0.22+mc1.21.1.jar",
        "Path":  "C:\\Users\\nacho\\AppData\\Roaming\\.minecraft\\mods\\variantsandventures-neoforge-1.0.22+mc1.21.1.jar",
        "Hash":  "bfdb2798d96f02abb57f0753ba13f41d42707b43"
    },
    {
        "Name":  "visuality-forge-2.1.0.jar",
        "Path":  "C:\\Users\\nacho\\AppData\\Roaming\\.minecraft\\mods\\visuality-forge-2.1.0.jar",
        "Hash":  "b400034ca8affe8f30b21935ae4ef74b1cf2fa29"
    },
    {
        "Name":  "VisualWorkbench-v21.1.1-1.21.1-NeoForge.jar",
        "Path":  "C:\\Users\\nacho\\AppData\\Roaming\\.minecraft\\mods\\VisualWorkbench-v21.1.1-1.21.1-NeoForge.jar",
        "Hash":  "74941456944461f39b10504ec9aed8c1e0fb7276"
    },
    {
        "Name":  "watut-neoforge-1.21.0-1.2.7.jar",
        "Path":  "C:\\Users\\nacho\\AppData\\Roaming\\.minecraft\\mods\\watut-neoforge-1.21.0-1.2.7.jar",
        "Hash":  "07cfb8fb1269f1eae1056492912e3544be979f62"
    },
    {
        "Name":  "Waves-1.21.x-1.6.jar",
        "Path":  "C:\\Users\\nacho\\AppData\\Roaming\\.minecraft\\mods\\Waves-1.21.x-1.6.jar",
        "Hash":  "744a47559d55f018f3906e3c03617d7f123764c2"
    },
    {
        "Name":  "WorldEditCUI-NeoForge-1.21.1+01-SNAPSHOT.jar",
        "Path":  "C:\\Users\\nacho\\AppData\\Roaming\\.minecraft\\mods\\WorldEditCUI-NeoForge-1.21.1+01-SNAPSHOT.jar",
        "Hash":  "5ed7b0950b0f3187d874d90fd9fed6828084cc53"
    },
    {
        "Name":  "wthit-1.21.1-neo-12.10.0.jar",
        "Path":  "C:\\Users\\nacho\\AppData\\Roaming\\.minecraft\\mods\\wthit-1.21.1-neo-12.10.0.jar",
        "Hash":  "1de8297108e03c98dd28688b1577020a76535696"
    },
    {
        "Name":  "xaerominimap-neoforge-1.21.1-25.3.5.jar",
        "Path":  "C:\\Users\\nacho\\AppData\\Roaming\\.minecraft\\mods\\xaerominimap-neoforge-1.21.1-25.3.5.jar",
        "Hash":  "b662f97a58d88d56780487a89bf65d9d0330869d"
    },
    {
        "Name":  "xaeroworldmap-neoforge-1.21.1-1.40.6.jar",
        "Path":  "C:\\Users\\nacho\\AppData\\Roaming\\.minecraft\\mods\\xaeroworldmap-neoforge-1.21.1-1.40.6.jar",
        "Hash":  "3001fb25d05142b3c35cccf5d6d52e662e303d66"
    },
    {
        "Name":  "yamlconfig-1.2-1.21-neoforge.jar",
        "Path":  "C:\\Users\\nacho\\AppData\\Roaming\\.minecraft\\mods\\yamlconfig-1.2-1.21-neoforge.jar",
        "Hash":  "7f0a3bb40950de3b1c634d88a199f5cbc5981013"
    },
    {
        "Name":  "yarrp-mc1.21.1-neoforge-v0.2.0.jar",
        "Path":  "C:\\Users\\nacho\\AppData\\Roaming\\.minecraft\\mods\\yarrp-mc1.21.1-neoforge-v0.2.0.jar",
        "Hash":  "c05ded82628db6f5c90e4fe1dc66f137c9ddd8cd"
    },
    {
        "Name":  "yet_another_config_lib_v3-3.8.1+1.21.1-neoforge.jar",
        "Path":  "C:\\Users\\nacho\\AppData\\Roaming\\.minecraft\\mods\\yet_another_config_lib_v3-3.8.1+1.21.1-neoforge.jar",
        "Hash":  "b566b99f019feae4df41651ff17f8b295fa72435"
    },
    {
        "Name":  "YungsApi-1.21.1-NeoForge-5.1.6.jar",
        "Path":  "C:\\Users\\nacho\\AppData\\Roaming\\.minecraft\\mods\\YungsApi-1.21.1-NeoForge-5.1.6.jar",
        "Hash":  "e1c394779fb9e038e4f7a1b4558d0432607d263b"
    },
    {
        "Name":  "YungsMenuTweaks-1.21.1-NeoForge-2.1.2.jar",
        "Path":  "C:\\Users\\nacho\\AppData\\Roaming\\.minecraft\\mods\\YungsMenuTweaks-1.21.1-NeoForge-2.1.2.jar",
        "Hash":  "da42e597009dae71faa37290e98b7b69bca52c25"
    }
]
